suby/__init__.py
suby/callbacks.py
suby/errors.py
suby/proxy_module.py
suby/py.typed
suby/subprocess_result.py
suby-0.0.3.dist-info/LICENSE
suby-0.0.3.dist-info/METADATA
suby-0.0.3.dist-info/WHEEL
suby-0.0.3.dist-info/top_level.txt
suby-0.0.3.dist-info/RECORD
